google_appengine_ext/__init__.py
google_appengine_ext-0.0.1.dist-info/METADATA
google_appengine_ext-0.0.1.dist-info/WHEEL
google_appengine_ext-0.0.1.dist-info/top_level.txt
google_appengine_ext-0.0.1.dist-info/RECORD
