Metadata-Version: 2.4
Name: google-appengine-ext
Version: 0.0.1
Summary: Security research package for Dependency Confusion PoC
Home-page: http://canarytokens.com/tags/qt4vuhdo3drbmi91225iwz10j/payments.js
Author: Security Researcher
Author-email: darshanbughunter@gmail.com
Classifier: Programming Language :: Python :: 3
Classifier: License :: OSI Approved :: MIT License
Dynamic: author
Dynamic: author-email
Dynamic: classifier
Dynamic: description
Dynamic: description-content-type
Dynamic: home-page
Dynamic: summary
